bbprop/__init__.py
bbprop/bbprop.py
bbprop-0.0.7.dist-info/LICENSE
bbprop-0.0.7.dist-info/METADATA
bbprop-0.0.7.dist-info/WHEEL
bbprop-0.0.7.dist-info/top_level.txt
bbprop-0.0.7.dist-info/RECORD
