Metadata-Version: 2.1
Name: bbprop
Version: 0.0.7
Summary: Hypothesis test for difference of beta-binomial proportions
Home-page: https://gitlab.com/aaylward/bbprop
Author: Anthony Aylward
Author-email: aaylward@salk.edu
License: UNKNOWN
Platform: UNKNOWN
Classifier: Programming Language :: Python :: 3
Classifier: License :: OSI Approved :: MIT License
Classifier: Operating System :: OS Independent
License-File: LICENSE
Requires-Dist: bbpmf
Requires-Dist: scipy
